cru_dse_utils/__init__.py
cru_dse_utils/auth.py
cru_dse_utils/bigquery.py
cru_dse_utils/dbt.py
cru_dse_utils/gcs.py
cru_dse_utils/general.py
cru_dse_utils-0.1.7.dist-info/LICENSE
cru_dse_utils-0.1.7.dist-info/METADATA
cru_dse_utils-0.1.7.dist-info/WHEEL
cru_dse_utils-0.1.7.dist-info/top_level.txt
cru_dse_utils-0.1.7.dist-info/RECORD
