Metadata-Version: 2.1
Name: cru-dse-utils
Version: 0.1.7
Summary: Cru DSE Python Utils
Author-email: Cru DSE Team <tony.guan@cru.org>
License: MIT License
Project-URL: repository, https://github.com/CruGlobal/dse-python-utils
Project-URL: homepage, https://github.com/CruGlobal/dse-python-utils
Classifier: License :: OSI Approved :: MIT License
Classifier: Programming Language :: Python
Classifier: Programming Language :: Python :: 3
Requires-Python: >=3.7
License-File: LICENSE
Requires-Dist: requests
Requires-Dist: google-auth
Requires-Dist: google-cloud-bigquery
Requires-Dist: google-cloud-storage
Requires-Dist: pandas
Provides-Extra: build
Requires-Dist: build; extra == "build"
Requires-Dist: twine; extra == "build"
Provides-Extra: dev
Requires-Dist: pytest; extra == "dev"
